star_conf/__init__.py
star_conf/datastructures.py
star_conf-0.1.1.dist-info/AUTHORS.rst
star_conf-0.1.1.dist-info/LICENSE
star_conf-0.1.1.dist-info/METADATA
star_conf-0.1.1.dist-info/WHEEL
star_conf-0.1.1.dist-info/top_level.txt
star_conf-0.1.1.dist-info/RECORD
