Metadata-Version: 2.1
Name: star-conf
Version: 0.1.1
Summary: Use Starlette's configuration as a standalone package
Home-page: https://gitlab.com/reedrichards/star_conf
Author: Robert Wendt
Author-email: rwendt1337@gmail.com
License: MIT license
Keywords: star_conf
Platform: UNKNOWN
Classifier: Development Status :: 2 - Pre-Alpha
Classifier: Intended Audience :: Developers
Classifier: License :: OSI Approved :: MIT License
Classifier: Natural Language :: English
Classifier: Programming Language :: Python :: 3
Classifier: Programming Language :: Python :: 3.6
Classifier: Programming Language :: Python :: 3.7
Requires-Python: >=3.6
